dramatiq_azure/__init__.py
dramatiq_azure/__version__.py
dramatiq_azure/asq.py
dramatiq_azure-0.3.2.dist-info/LICENSE
dramatiq_azure-0.3.2.dist-info/METADATA
dramatiq_azure-0.3.2.dist-info/WHEEL
dramatiq_azure-0.3.2.dist-info/RECORD
