Metadata-Version: 2.3
Name: dramatiq_azure
Version: 0.3.2
Summary: Azure Queue Brokers for Dramatiq
License: Apache-2.0
Keywords: dramatiq,azure,queue,broker
Author: Stanislas H.B. Sodonon
Author-email: stanislas.sodonon@gmail.com
Requires-Python: >=3.9,<4.0
Classifier: License :: OSI Approved :: Apache Software License
Classifier: Programming Language :: Python :: 3
Classifier: Programming Language :: Python :: 3.9
Classifier: Programming Language :: Python :: 3.10
Classifier: Programming Language :: Python :: 3.11
Classifier: Programming Language :: Python :: 3.12
Classifier: Programming Language :: Python :: 3.13
Provides-Extra: identity
Requires-Dist: azure-core (>=1.34.0,<2.0.0)
Requires-Dist: azure-identity (==1.22.0) ; extra == "identity"
Requires-Dist: azure-storage-queue (>=12.12.0,<13.0.0)
Requires-Dist: dramatiq (>=1.17.1,<2.0.0)
Project-URL: Repository, https://github.com/bidossessi/dramatiq-azure
